hyperx/__init__.py
hyperx/api/__init__.py
hyperx/api/types/__init__.py
hyperx/library/__init__.py
hyperx/library/find.py
hyperx/library/library.py
hyperx/utils/__init__.py
hyperx/utils/utils.py
hyperx/version/__init__.py
hyperx/version/version.py
hyperx-2025.1.4.dist-info/METADATA
hyperx-2025.1.4.dist-info/WHEEL
hyperx-2025.1.4.dist-info/top_level.txt
hyperx-2025.1.4.dist-info/RECORD
