Metadata-Version: 2.4
Name: hyperx
Version: 2025.1.4
Summary: HyperX scripting for Python
Author-email: Kelly Ann Smith <kellyann.smith@collieraerospace.com>, Noah Prezant <noah.prezant@collieraerospace.com>
Project-URL: Homepage, https://collieraerospace.com
Classifier: Programming Language :: Python :: 3
Classifier: License :: OSI Approved :: MIT License
Classifier: Operating System :: OS Independent
Requires-Python: >=3.7
Requires-Dist: pythonnet>=3.0.1
